Workbook

Sheet TCD Encours
A1: REPORTING ENCOURS — CALCUL MANUEL SIMULÉ
A2: Arrêté 31/03/2026 · la colonne Excel reproduit une formule héritée à corriger.
A4: categorie | B4: encours_excel_legacy | C4: encours_sql_corrige | D4: contrats | F4: Écart constaté
A5: auto | B5: 29417038 | C5: 31248744 | D5: 1188 | F5: L’ancienne formule soustrait les encaissements totaux (capital + intérêts) du principal financé. La migration conserve l’encours restant en capital via l’échéancier amortissable.
A6: bateau | B6: 14132393 | C6: 15048484 | D6: 161
A7: materiel | B7: 37409878 | C7: 39363749 | D7: 611

Sheet Détail contrats
A1: contrat_id | B1: client_id | C1: territoire | D1: categorie | E1: produit | F1: date_debut | G1: montant_finance | H1: encours_excel_legacy | I1: encours_sql | J1: statut
A2: CTR-00001 | B2: CLI-00993 | C2: Île-de-France | D2: auto | E2: LOA | F2: 2024-10-01 | G2: 46926.24 | H2: =MAX(0,G2-SUMIFS('Paiements contrat'!$B:$B,'Paiements contrat'!$A:$A,A2)) | I2: 25285.41 | J2: contentieux
A3: CTR-00002 | B3: CLI-00113 | C3: Guyane | D3: auto | E3: LLD | F3: 2026-03-06 | G3: 10617.13 | H3: =MAX(0,G3-SUMIFS('Paiements contrat'!$B:$B,'Paiements contrat'!$A:$A,A3)) | I3: 10617.13 | J3: actif
A4: CTR-00003 | B4: CLI-00562 | C4: Île-de-France | D4: auto | E4: LOA | F4: 2024-04-25 | G4: 71327.64 | H4: =MAX(0,G4-SUMIFS('Paiements contrat'!$B:$B,'Paiements contrat'!$A:$A,A4)) | I4: 9197.3 | J4: actif
A5: CTR-00004 | B5: CLI-01046 | C5: Île-de-France | D5: materiel | E5: crédit-bail | F5: 2026-03-12 | G5: 93597.2 | H5: =MAX(0,G5-SUMIFS('Paiements contrat'!$B:$B,'Paiements contrat'!$A:$A,A5)) | I5: 93597.2 | J5: actif
A6: CTR-00005 | B6: CLI-00161 | C6: Guadeloupe | D6: auto | E6: LLD | F6: 2024-08-04 | G6: 46959.02 | H6: =MAX(0,G6-SUMIFS('Paiements contrat'!$B:$B,'Paiements contrat'!$A:$A,A6)) | I6: 4472.0324 | J6: soldé
A7: CTR-00006 | B7: CLI-01277 | C7: Réunion | D7: auto | E7: LLD | F7: 2025-01-21 | G7: 35077.62 | H7: =MAX(0,G7-SUMIFS('Paiements contrat'!$B:$B,'Paiements contrat'!$A:$A,A7)) | I7: 19280.87 | J7: actif
A8: CTR-00007 | B8: CLI-01173 | C8: Île-de-France | D8: auto | E8: LOA | F8: 2024-10-13 | G8: 12330.09 | H8: =MAX(0,G8-SUMIFS('Paiements contrat'!$B:$B,'Paiements contrat'!$A:$A,A8)) | I8: 4344.43 | J8: actif
A9: CTR-00008 | B9: CLI-00490 | C9: Martinique | D9: auto | E9: LOA | F9: 2025-10-10 | G9: 24526.21 | H9: =MAX(0,G9-SUMIFS('Paiements contrat'!$B:$B,'Paiements contrat'!$A:$A,A9)) | I9: 19549.09 | J9: actif
A10: CTR-00009 | B10: CLI-01140 | C10: Île-de-France | D10: auto | E10: LOA | F10: 2025-10-10 | G10: 66633.77 | H10: =MAX(0,G10-SUMIFS('Paiements contrat'!$B:$B,'Paiements contrat'!$A:$A,A10)) | I10: 55789.6 | J10: actif
A11: CTR-00010 | B11: CLI-00423 | C11: Île-de-France | D11: bateau | E11: LOA | F11: 2025-08-14 | G11: 272997.61 | H11: =MAX(0,G11-SUMIFS('Paiements contrat'!$B:$B,'Paiements contrat'!$A:$A,A11)) | I11: 252068.45 | J11: actif
A12: CTR-00011 | B12: CLI-00068 | C12: Île-de-France | D12: auto | E12: LOA | F12: 2024-05-11 | G12: 50087.5 | H12: =MAX(0,G12-SUMIFS('Paiements contrat'!$B:$B,'Paiements contrat'!$A:$A,A12)) | I12: 21393.52 | J12: actif
A13: CTR-00012 | B13: CLI-01204 | C13: Île-de-France | D13: auto | E13: LOA | F13: 2024-10-13 | G13: 10700.13 | H13: =MAX(0,G13-SUMIFS('Paiements contrat'!$B:$B,'Paiements contrat'!$A:$A,A13)) | I13: 1985.4068 | J13: actif
... A1961: CTR-02000 | B1961: CLI-00505 | C1961: Martinique | D1961: materiel | E1961: crédit-bail | F1961: 2025-01-05 | G1961: 104702 | H1961: =MAX(0,G1961-SUMIFS('Paiements contrat'!$B:$B,'Paiements contrat'!$A:$A,A1961)) | I1961: 8734.85 | J1961: soldé

Sheet Paiements contrat
A1: contrat_id | B1: paiements_cumules
A2: CTR-00001 | B2: 23186.81
A3: CTR-00003 | B3: 65897.37
A4: CTR-00005 | B4: 44240.44
A5: CTR-00006 | B5: 16769.61
A6: CTR-00007 | B6: 8980.96
A7: CTR-00008 | B7: 5287.15
A8: CTR-00009 | B8: 11494.14
A9: CTR-00010 | B9: 24982.2
A10: CTR-00011 | B10: 30725.73
A11: CTR-00012 | B11: 9362.53
A12: CTR-00013 | B12: 16951.98
A13: CTR-00014 | B13: 14978.64
... A1867: CTR-02000 | B1867: 97407.25
